{
  "meta": {
    "generated_at": "2026-06-23T23:33:21.250Z",
    "next_update_at": "2026-06-24T00:33:21.250Z",
    "sources": [
      "WAQI",
      "Open-Meteo"
    ],
    "location": {
      "name": "Patna",
      "state": "Bihar",
      "country": "India",
      "lat": 25.5941,
      "lon": 85.1376
    }
  },
  "current": {
    "aqi": 21,
    "category": "Good",
    "dominant_pollutant": "o3",
    "station": {
      "name": "IGSC Planetarium Complex, Patna, India",
      "waqi_id": 8674
    },
    "pollutants": [
      {
        "id": "pm25",
        "display_name": "PM2.5",
        "value": 101.5,
        "unit": "µg/m³",
        "category": "Poor"
      },
      {
        "id": "pm10",
        "display_name": "PM10",
        "value": 128.5,
        "unit": "µg/m³",
        "category": "Moderate"
      },
      {
        "id": "no2",
        "display_name": "NO₂",
        "value": 49.6,
        "unit": "µg/m³",
        "category": "Satisfactory"
      },
      {
        "id": "so2",
        "display_name": "SO₂",
        "value": 20.8,
        "unit": "µg/m³",
        "category": "Good"
      },
      {
        "id": "co",
        "display_name": "CO",
        "value": 0.48,
        "unit": "mg/m³",
        "category": "Good"
      },
      {
        "id": "o3",
        "display_name": "O₃",
        "value": 24,
        "unit": "µg/m³",
        "category": "Good"
      }
    ]
  },
  "forecast": {
    "hourly": [
      {
        "time": "2026-06-24T05:00+05:30",
        "pm25": 103.4,
        "pm10": 129,
        "no2": 45.7,
        "o3": 29,
        "so2": 20.3,
        "co": 0.42
      },
      {
        "time": "2026-06-24T06:00+05:30",
        "pm25": 97.8,
        "pm10": 118.7,
        "no2": 37.7,
        "o3": 51,
        "so2": 20.8,
        "co": 0.38
      },
      {
        "time": "2026-06-24T07:00+05:30",
        "pm25": 82,
        "pm10": 106.2,
        "no2": 27.8,
        "o3": 82,
        "so2": 21.7,
        "co": 0.35
      },
      {
        "time": "2026-06-24T08:00+05:30",
        "pm25": 66.8,
        "pm10": 88.2,
        "no2": 19.1,
        "o3": 114,
        "so2": 21.4,
        "co": 0.33
      },
      {
        "time": "2026-06-24T09:00+05:30",
        "pm25": 55.9,
        "pm10": 71.9,
        "no2": 12.5,
        "o3": 146,
        "so2": 18.8,
        "co": 0.3
      },
      {
        "time": "2026-06-24T10:00+05:30",
        "pm25": 51,
        "pm10": 67.1,
        "no2": 7.2,
        "o3": 178,
        "so2": 15.1,
        "co": 0.29
      },
      {
        "time": "2026-06-24T11:00+05:30",
        "pm25": 49,
        "pm10": 68.9,
        "no2": 3.5,
        "o3": 199,
        "so2": 11.9,
        "co": 0.27
      },
      {
        "time": "2026-06-24T12:00+05:30",
        "pm25": 47.7,
        "pm10": 78.9,
        "no2": 1.5,
        "o3": 201,
        "so2": 9.9,
        "co": 0.25
      },
      {
        "time": "2026-06-24T13:00+05:30",
        "pm25": 49.1,
        "pm10": 103.1,
        "no2": 1.1,
        "o3": 192,
        "so2": 8.6,
        "co": 0.22
      },
      {
        "time": "2026-06-24T14:00+05:30",
        "pm25": 49.7,
        "pm10": 120.6,
        "no2": 2.4,
        "o3": 179,
        "so2": 7.8,
        "co": 0.21
      },
      {
        "time": "2026-06-24T15:00+05:30",
        "pm25": 49.2,
        "pm10": 124.3,
        "no2": 5.1,
        "o3": 165,
        "so2": 7.3,
        "co": 0.21
      },
      {
        "time": "2026-06-24T16:00+05:30",
        "pm25": 48.9,
        "pm10": 121.5,
        "no2": 9.5,
        "o3": 147,
        "so2": 7.3,
        "co": 0.22
      },
      {
        "time": "2026-06-24T17:00+05:30",
        "pm25": 51.8,
        "pm10": 101.3,
        "no2": 16.4,
        "o3": 128,
        "so2": 8.9,
        "co": 0.27
      },
      {
        "time": "2026-06-24T18:00+05:30",
        "pm25": 65,
        "pm10": 108.7,
        "no2": 29.4,
        "o3": 105,
        "so2": 13.5,
        "co": 0.41
      },
      {
        "time": "2026-06-24T19:00+05:30",
        "pm25": 82.9,
        "pm10": 130.9,
        "no2": 44.9,
        "o3": 80,
        "so2": 19.7,
        "co": 0.58
      },
      {
        "time": "2026-06-24T20:00+05:30",
        "pm25": 91.7,
        "pm10": 136.4,
        "no2": 53.3,
        "o3": 65,
        "so2": 23.7,
        "co": 0.7
      },
      {
        "time": "2026-06-24T21:00+05:30",
        "pm25": 88.9,
        "pm10": 124.8,
        "no2": 48.1,
        "o3": 67,
        "so2": 23.6,
        "co": 0.72
      },
      {
        "time": "2026-06-24T22:00+05:30",
        "pm25": 82.4,
        "pm10": 110.4,
        "no2": 35.9,
        "o3": 78,
        "so2": 21.4,
        "co": 0.68
      },
      {
        "time": "2026-06-24T23:00+05:30",
        "pm25": 79.6,
        "pm10": 101.5,
        "no2": 26.2,
        "o3": 85,
        "so2": 19.3,
        "co": 0.64
      },
      {
        "time": "2026-06-25T00:00+05:30",
        "pm25": 78.9,
        "pm10": 97.1,
        "no2": 22.8,
        "o3": 83,
        "so2": 18.2,
        "co": 0.61
      },
      {
        "time": "2026-06-25T01:00+05:30",
        "pm25": 78.5,
        "pm10": 93.8,
        "no2": 21.9,
        "o3": 76,
        "so2": 17.3,
        "co": 0.57
      },
      {
        "time": "2026-06-25T02:00+05:30",
        "pm25": 78.5,
        "pm10": 93.1,
        "no2": 22.3,
        "o3": 70,
        "so2": 16.6,
        "co": 0.53
      },
      {
        "time": "2026-06-25T03:00+05:30",
        "pm25": 80.3,
        "pm10": 94.1,
        "no2": 24.6,
        "o3": 61,
        "so2": 16.1,
        "co": 0.5
      },
      {
        "time": "2026-06-25T04:00+05:30",
        "pm25": 84.5,
        "pm10": 97.1,
        "no2": 28.2,
        "o3": 53,
        "so2": 15.9,
        "co": 0.47
      },
      {
        "time": "2026-06-25T05:00+05:30",
        "pm25": 87.3,
        "pm10": 97.3,
        "no2": 29.1,
        "o3": 56,
        "so2": 16.2,
        "co": 0.45
      },
      {
        "time": "2026-06-25T06:00+05:30",
        "pm25": 86.4,
        "pm10": 97.6,
        "no2": 25,
        "o3": 79,
        "so2": 17.7,
        "co": 0.42
      },
      {
        "time": "2026-06-25T07:00+05:30",
        "pm25": 76.1,
        "pm10": 92.2,
        "no2": 18.3,
        "o3": 113,
        "so2": 19.7,
        "co": 0.4
      },
      {
        "time": "2026-06-25T08:00+05:30",
        "pm25": 67.5,
        "pm10": 88.5,
        "no2": 12.5,
        "o3": 146,
        "so2": 20.8,
        "co": 0.37
      },
      {
        "time": "2026-06-25T09:00+05:30",
        "pm25": 64.3,
        "pm10": 90.3,
        "no2": 8.7,
        "o3": 178,
        "so2": 20.1,
        "co": 0.34
      },
      {
        "time": "2026-06-25T10:00+05:30",
        "pm25": 63.1,
        "pm10": 97.8,
        "no2": 5.8,
        "o3": 209,
        "so2": 18.4,
        "co": 0.31
      }
    ]
  }
}